doc/Makefile
doc/README.rst
doc/api.rst
doc/bibliography.rst
doc/conf.py
doc/contributing.rst
doc/debugging.rst
doc/efficiency.rst
doc/faq.rst
doc/framework.rst
doc/index.rst
doc/install-adv.rst
doc/install.rst
doc/macro.rst
doc/make.bat
doc/notice.rst
doc/prereqs.rst
doc/references.bib
doc/reporting.rst
doc/requirements.in
doc/requirements.txt
doc/rmessageix.rst
doc/sharing.rst
doc/time.rst
doc/tutorials.rst
doc/usage.rst
doc/whatsnew.rst
doc/_static/combined-logo-white.svg
doc/_static/custom.css
doc/_static/iiasa-logo-white.svg
doc/_static/ix_components.png
doc/_static/ix_features.svg
doc/_static/macro-calibrate.svg
doc/_static/messageix-community-logo-white.svg
doc/_static/messageix-community-logo.svg
doc/_static/messageix-favicon.svg
doc/_static/messageix-logo-white.svg
doc/_static/messageix-logo.svg
doc/_static/storage.png
doc/_static/usage_figures/1-s2.0-S2210670721005333-gr19_lrg.jpg
doc/_static/usage_figures/1-s2.0-S2352152X2400834X-gr1.jpg
doc/_static/usage_figures/10.1016-j.est.2022.104587.JPG
doc/_static/usage_figures/10.1016-j.scs.2021.103257.jpg
doc/_static/usage_figures/10.1038-s41560-018-0172-6.webp
doc/_static/usage_figures/10.1038-s41560-018-0179-z.webp
doc/_static/usage_figures/10.3390-en12081483.png
doc/_static/usage_figures/41560_2021_904.webp
doc/contrib/cla.rst
doc/contrib/release.rst
doc/contrib/tutorial.rst
doc/contrib/version.rst
doc/contrib/video.rst
doc/contrib/video/install.rst
doc/tools/add_year.rst
doc/tools/lp_diag.rst
doc/tools/migrate.rst
doc/tools/sankey.rst
message_ix/__init__.py
message_ix/cli.py
message_ix/core.py
message_ix/macro.py
message_ix/models.py
message_ix/py.typed
message_ix/utils.py
message_ix/model/MACRO_run.gms
message_ix/model/MESSAGE-MACRO_run.gms
message_ix/model/MESSAGE_master.gms
message_ix/model/MESSAGE_project.gpr
message_ix/model/MESSAGE_run.gms
message_ix/model/conopt.opt
message_ix/model/version.gms
message_ix/model/MACRO/macro_calibration.gms
message_ix/model/MACRO/macro_core.gms
message_ix-3.11.1.dist-info/licenses/AUTHORS.md
message_ix-3.11.1.dist-info/licenses/LICENSE
message_ix-3.11.1.dist-info/licenses/NOTICE.rst
message_ix-3.11.1.dist-info/METADATA
message_ix-3.11.1.dist-info/WHEEL
message_ix-3.11.1.dist-info/entry_points.txt
message_ix-3.11.1.dist-info/top_level.txt
message_ix-3.11.1.dist-info/RECORD
