Metadata-Version: 2.4
Name: message_ix
Version: 3.11.1
Summary: The MESSAGEix integrated assessment model framework
Author: IIASA Energy, Climate, and Environment (ECE) Program
Maintainer-email: Paul Natsuo Kishimoto <mail@paul.kishimoto.name>, Fridolin Glatter <glatter@iiasa.ac.at>
License-Expression: Apache-2.0
Project-URL: Documentation, https://docs.messageix.org
Project-URL: Release notes, https://docs.messageix.org/en/stable/whatsnew.html
Project-URL: Repository, https://github.com/iiasa/message_ix
Project-URL: Issue tracker, https://github.com/iiasa/message_ix/issues
Classifier: Development Status :: 5 - Production/Stable
Classifier: Intended Audience :: Developers
Classifier: Intended Audience :: Science/Research
Classifier: Natural Language :: English
Classifier: Operating System :: OS Independent
Classifier: Programming Language :: Python
Classifier: Programming Language :: Python :: 3
Classifier: Programming Language :: Python :: 3.9
Classifier: Programming Language :: Python :: 3.10
Classifier: Programming Language :: Python :: 3.11
Classifier: Programming Language :: Python :: 3.12
Classifier: Programming Language :: Python :: 3.13
Classifier: Programming Language :: R
Classifier: Topic :: Scientific/Engineering
Classifier: Topic :: Scientific/Engineering :: Information Analysis
Requires-Python: >=3.9
License-File: LICENSE
License-File: NOTICE.rst
License-File: AUTHORS.md
Requires-Dist: click
Requires-Dist: ixmp>=3.11
Requires-Dist: genno[pyam]>=1.20
Requires-Dist: numpy
Requires-Dist: pandas>=1.2
Requires-Dist: PyYAML
Requires-Dist: scipy
Provides-Extra: docs
Requires-Dist: genno>=1.26; extra == "docs"
Requires-Dist: GitPython; extra == "docs"
Requires-Dist: message_ix[ixmp4,report]; extra == "docs"
Requires-Dist: numpydoc; extra == "docs"
Requires-Dist: sphinx>=4.0; extra == "docs"
Requires-Dist: sphinx_rtd_theme; extra == "docs"
Requires-Dist: sphinxcontrib-bibtex; extra == "docs"
Provides-Extra: ixmp4
Requires-Dist: ixmp[ixmp4]; extra == "ixmp4"
Provides-Extra: report
Requires-Dist: ixmp[report]; extra == "report"
Provides-Extra: sankey
Requires-Dist: plotly; extra == "sankey"
Provides-Extra: tests
Requires-Dist: ixmp[tests]; extra == "tests"
Requires-Dist: message_ix[docs,tutorial]; extra == "tests"
Requires-Dist: pint; extra == "tests"
Requires-Dist: pooch; extra == "tests"
Requires-Dist: pyam-iamc>=0.6; extra == "tests"
Requires-Dist: pytest>=5; extra == "tests"
Requires-Dist: pytest-cov; extra == "tests"
Requires-Dist: pytest-rerunfailures; extra == "tests"
Requires-Dist: pytest-xdist; extra == "tests"
Provides-Extra: tutorial
Requires-Dist: message_ix[report,sankey]; extra == "tutorial"
Requires-Dist: jupyter; extra == "tutorial"
Requires-Dist: matplotlib; extra == "tutorial"
Dynamic: license-file
